ezperm/__init__.py
ezperm/decorators.py
ezperm/django/__init__.py
ezperm/django/models.py
ezperm/django/views.py
ezperm/enums.py
ezperm/interfaces.py
ezperm-0.1.2.dist-info/LICENSE.md
ezperm-0.1.2.dist-info/METADATA
ezperm-0.1.2.dist-info/WHEEL
ezperm-0.1.2.dist-info/RECORD
