Metadata-Version: 2.1
Name: ezperm
Version: 0.1.2
Summary: Permissions made easy
Home-page: https://github.com/VojtechPetru/ezperm
License: MIT
Keywords: permissions,django
Author: vojtech
Author-email: petru.vojtech@gmail.com
Requires-Python: >=3.8,<4.0
Classifier: License :: OSI Approved :: MIT License
Classifier: Programming Language :: Python :: 3
Classifier: Programming Language :: Python :: 3.8
Classifier: Programming Language :: Python :: 3.9
Classifier: Programming Language :: Python :: 3.10
Classifier: Programming Language :: Python :: 3.11
Classifier: Programming Language :: Python :: 3.12
Provides-Extra: django
Project-URL: Repository, https://github.com/VojtechPetru/ezperm
